Lingzu0dayWenku/README.md
Lingzu0dayWenku/__init__.py
Lingzu0dayWenku/__main__.py
Lingzu0dayWenku/file.epub
Lingzu0dayWenku/index.html
Lingzu0dayWenku/css/__init__.py
Lingzu0dayWenku/css/annotations.css
Lingzu0dayWenku/css/main.css
Lingzu0dayWenku/css/normalize.css
Lingzu0dayWenku/css/popup.css
Lingzu0dayWenku/font/__init__.py
Lingzu0dayWenku/font/fontello.eot
Lingzu0dayWenku/font/fontello.svg
Lingzu0dayWenku/font/fontello.ttf
Lingzu0dayWenku/font/fontello.woff
Lingzu0dayWenku/img/__init__.py
Lingzu0dayWenku/img/annotator-glyph-sprite.png
Lingzu0dayWenku/img/annotator-icon-sprite.png
Lingzu0dayWenku/img/apple-touch-icon.png
Lingzu0dayWenku/img/cancelfullscreen.png
Lingzu0dayWenku/img/close.png
Lingzu0dayWenku/img/fullscreen.png
Lingzu0dayWenku/img/loader.gif
Lingzu0dayWenku/img/menu-icon.png
Lingzu0dayWenku/img/save.png
Lingzu0dayWenku/img/saved.png
Lingzu0dayWenku/img/settings-s.png
Lingzu0dayWenku/img/settings.png
Lingzu0dayWenku/img/star.png
Lingzu0dayWenku/js/__init__.py
Lingzu0dayWenku/js/epub.js
Lingzu0dayWenku/js/epub.min.js
Lingzu0dayWenku/js/epub.min.map
Lingzu0dayWenku/js/hooks.min.js
Lingzu0dayWenku/js/hooks.min.map
Lingzu0dayWenku/js/reader.js
Lingzu0dayWenku/js/reader.js.map
Lingzu0dayWenku/js/reader.min.js
Lingzu0dayWenku/js/reader.min.map
Lingzu0dayWenku/js/hooks/__init__.py
Lingzu0dayWenku/js/hooks/extensions/__init__.py
Lingzu0dayWenku/js/hooks/extensions/highlight.js
Lingzu0dayWenku/js/libs/__init__.py
Lingzu0dayWenku/js/libs/jquery.min.js
Lingzu0dayWenku/js/libs/localforage.min.js
Lingzu0dayWenku/js/libs/screenfull.js
Lingzu0dayWenku/js/libs/screenfull.min.js
Lingzu0dayWenku/js/libs/zip.min.js
Lingzu0dayWenku/js/plugins/__init__.py
Lingzu0dayWenku/js/plugins/hypothesis.js
Lingzu0dayWenku/js/plugins/search.js
lingzu_0day_wenku-2024.3.5.0.dist-info/METADATA
lingzu_0day_wenku-2024.3.5.0.dist-info/WHEEL
lingzu_0day_wenku-2024.3.5.0.dist-info/entry_points.txt
lingzu_0day_wenku-2024.3.5.0.dist-info/top_level.txt
lingzu_0day_wenku-2024.3.5.0.dist-info/RECORD
